chinus_uploads/__init__.py
chinus_uploads/upload.py
chinus_uploads/gits/__init__.py
chinus_uploads/gits/status.py
chinus_uploads/uploads/__init__.py
chinus_uploads/uploads/uploads.py
chinus_uploads-1.3.5.dist-info/METADATA
chinus_uploads-1.3.5.dist-info/WHEEL
chinus_uploads-1.3.5.dist-info/top_level.txt
chinus_uploads-1.3.5.dist-info/RECORD
